Metadata-Version: 2.4
Name: jarvis-runtime
Version: 0.1.0a5
Summary: Jarvis Agent Runtime for executing ARP-style flows with planning support.
Author: Agent Runtime Protocol
License: MIT License
Project-URL: Repository, https://github.com/AgentRuntimeProtocol/JARVIS_Runtime
Project-URL: Issues, https://github.com/AgentRuntimeProtocol/JARVIS_Runtime/issues
Requires-Python: >=3.10
License-File: LICENSE
Requires-Dist: jarvis-model==0.1.0a5
Provides-Extra: inproc
Requires-Dist: jarvis-tool-registry>=0.1.0a5; extra == "inproc"
Provides-Extra: openai
Requires-Dist: openai>=1.0.0; extra == "openai"
Provides-Extra: dev
Requires-Dist: pyright>=1.1.0; extra == "dev"
Requires-Dist: pytest>=7; extra == "dev"
Requires-Dist: pytest-cov>=4; extra == "dev"
Dynamic: license-file
